jenkins_yml/__init__.py
jenkins_yml/job.py
jenkins_yml/runner.py
jenkins_yml/templates/freestyle.xml
jenkins_yml/templates/job.j2
jenkins_yml/templates/matrix.xml
jenkins_yml-2.34.dist-info/DESCRIPTION.rst
jenkins_yml-2.34.dist-info/METADATA
jenkins_yml-2.34.dist-info/RECORD
jenkins_yml-2.34.dist-info/WHEEL
jenkins_yml-2.34.dist-info/entry_points.txt
jenkins_yml-2.34.dist-info/metadata.json
jenkins_yml-2.34.dist-info/top_level.txt
