Metadata-Version: 2.0
Name: jenkins-yml
Version: 2.34
Summary: Define Jenkins jobs from repository
Home-page: https://github.com/novafloss/jenkins-yml
Author: Étienne BERSAC
Author-email: etienne.bersac@people-doc.com
License: GPL v3 or later
Keywords: jenkins
Platform: UNKNOWN
Classifier: Development Status :: 4 - Beta
Classifier: Environment :: Console
Classifier: Intended Audience :: Developers
Classifier: Programming Language :: Python
Requires-Dist: pyyaml
Provides-Extra: release
Requires-Dist: wheel; extra == 'release'
Requires-Dist: zest.releaser; extra == 'release'
Provides-Extra: renderer
Requires-Dist: jinja2; extra == 'renderer'
